nba_history/__init__.py
nba_history/player_data.py
nba_history/team_data.py
nba_history-1.1.7.dist-info/LICENSE
nba_history-1.1.7.dist-info/METADATA
nba_history-1.1.7.dist-info/WHEEL
nba_history-1.1.7.dist-info/top_level.txt
nba_history-1.1.7.dist-info/RECORD
