Metadata-Version: 2.1
Name: nba-history
Version: 1.1.7
Summary: UNKNOWN
Home-page: https://github.com/odonnell31/nba_history
Author: Michael ODonnell
Author-email: mro4354@gmail.com
License: UNKNOWN
Project-URL: Bug Tracker, https://github.com/odonnell31/nba_history
Keywords: nba,basketball,scraping,data mining,basketball reference,bs4
Platform: UNKNOWN
Classifier: Programming Language :: Python
Classifier: Programming Language :: Python :: 3
Classifier: License :: OSI Approved :: MIT License
Classifier: Operating System :: OS Independent
Classifier: Intended Audience :: Developers
Classifier: Natural Language :: English
Requires-Python: >=3.6
License-File: LICENSE
Requires-Dist: requests
Requires-Dist: beautifulsoup4
Requires-Dist: pandas
